{"skeleton":{"hash":"+AXolJ7ch1cDpBe+6K/mllRj2zQ","spine":"3.8.99","x":-81,"y":-81.68,"width":176.16,"height":180.66,"images":"./images/","audio":""},"bones":[{"name":"root"},{"name":"bone_phan","parent":"root"},{"name":"phan","parent":"bone_phan"},{"name":"phan2","parent":"bone_phan","rotation":-74.97}],"slots":[{"name":"phan","bone":"phan","color":"ffffff00","attachment":"phan"},{"name":"phan2","bone":"phan2","color":"ffffff00","attachment":"phan"}],"skins":[{"name":"default","attachments":{"phan":{"phan":{"x":-6,"y":11,"width":150,"height":138}},"phan2":{"phan":{"x":-6,"y":11,"width":150,"height":138}}}}],"animations":{"in_out":{"slots":{"phan":{"color":[{"color":"ffffff00","curve":0.29,"c3":0.629,"c4":0.38},{"time":0.5,"color":"ffffffff","curve":"stepped"},{"time":1.6667,"color":"ffffffff","curve":0.377,"c2":0.61,"c3":0.72},{"time":3,"color":"ffffff00"}]},"phan2":{"color":[{"color":"ffffff00","curve":0.29,"c3":0.629,"c4":0.38},{"time":0.1667,"color":"ffffffff","curve":"stepped"},{"time":0.9667,"color":"ffffffff","curve":0.377,"c2":0.61,"c3":0.72},{"time":2.1667,"color":"ffffff00"}]}},"bones":{"phan":{"rotate":[{"curve":0.25,"c3":0.75},{"time":3,"angle":38.96}],"translate":[{"curve":0.243,"c3":0.689,"c4":0.75},{"time":3,"x":-13.52,"y":42.5}],"scale":[{"x":0.412,"y":0.412,"curve":0.271,"c2":0.12,"c3":0.681,"c4":0.72},{"time":3,"x":2.263,"y":2.263}]},"phan2":{"rotate":[{"curve":0.25,"c3":0.75},{"time":2.1667,"angle":38.96}],"scale":[{"x":0.412,"y":0.412,"curve":0.271,"c2":0.12,"c3":0.681,"c4":0.72},{"time":2.1667,"x":3.201,"y":3.201}]}}}}}